<?xml version="1.0" encoding="UTF-8" ?>
<XMLDB PATH="mod/individualfeedback/db" VERSION="20160511" COMMENT="XMLDB file for Moodle mod/individualfeedback"
    xmlns:xsi="http://www.w3.org/2001/XMLSchema-instance"
    xsi:noNamespaceSchemaLocation="../../../lib/xmldb/xmldb.xsd"
>
  <TABLES>
    <TABLE NAME="individualfeedback" COMMENT="all individualfeedbacks">
      <FIELDS>
        <FIELD NAME="id" TYPE="int" LENGTH="10" NOTNULL="true" SEQUENCE="true"/>
        <FIELD NAME="course" TYPE="int" LENGTH="10" NOTNULL="true" DEFAULT="0" SEQUENCE="false"/>
        <FIELD NAME="name" TYPE="char" LENGTH="255" NOTNULL="true" SEQUENCE="false"/>
        <FIELD NAME="intro" TYPE="text" NOTNULL="true" SEQUENCE="false"/>
        <FIELD NAME="introformat" TYPE="int" LENGTH="4" NOTNULL="true" DEFAULT="0" SEQUENCE="false"/>
        <FIELD NAME="anonymous" TYPE="int" LENGTH="1" NOTNULL="true" DEFAULT="1" SEQUENCE="false"/>
        <FIELD NAME="email_notification" TYPE="int" LENGTH="1" NOTNULL="true" DEFAULT="1" SEQUENCE="false"/>
        <FIELD NAME="multiple_submit" TYPE="int" LENGTH="1" NOTNULL="true" DEFAULT="1" SEQUENCE="false"/>
        <FIELD NAME="autonumbering" TYPE="int" LENGTH="1" NOTNULL="true" DEFAULT="1" SEQUENCE="false"/>
        <FIELD NAME="site_after_submit" TYPE="char" LENGTH="255" NOTNULL="true" SEQUENCE="false"/>
        <FIELD NAME="page_after_submit" TYPE="text" NOTNULL="true" SEQUENCE="false"/>
        <FIELD NAME="page_after_submitformat" TYPE="int" LENGTH="2" NOTNULL="true" DEFAULT="0" SEQUENCE="false"/>
        <FIELD NAME="publish_stats" TYPE="int" LENGTH="1" NOTNULL="true" DEFAULT="0" SEQUENCE="false"/>
        <FIELD NAME="timeopen" TYPE="int" LENGTH="10" NOTNULL="true" DEFAULT="0" SEQUENCE="false"/>
        <FIELD NAME="timeclose" TYPE="int" LENGTH="10" NOTNULL="true" DEFAULT="0" SEQUENCE="false"/>
        <FIELD NAME="timemodified" TYPE="int" LENGTH="10" NOTNULL="true" DEFAULT="0" SEQUENCE="false"/>
        <FIELD NAME="completionsubmit" TYPE="int" LENGTH="1" NOTNULL="true" DEFAULT="0" SEQUENCE="false" COMMENT="If this field is set to 1, then the activity will be automatically marked as 'complete' once the user submits their choice."/>
      </FIELDS>
      <KEYS>
        <KEY NAME="primary" TYPE="primary" FIELDS="id" COMMENT="Primary key for individualfeedback"/>
      </KEYS>
      <INDEXES>
        <INDEX NAME="course" UNIQUE="false" FIELDS="course"/>
      </INDEXES>
    </TABLE>
    <TABLE NAME="individualfeedback_template" COMMENT="templates of individualfeedbackstructures">
      <FIELDS>
        <FIELD NAME="id" TYPE="int" LENGTH="10" NOTNULL="true" SEQUENCE="true"/>
        <FIELD NAME="course" TYPE="int" LENGTH="10" NOTNULL="true" DEFAULT="0" SEQUENCE="false"/>
        <FIELD NAME="ispublic" TYPE="int" LENGTH="1" NOTNULL="true" DEFAULT="0" SEQUENCE="false"/>
        <FIELD NAME="name" TYPE="char" LENGTH="255" NOTNULL="true" SEQUENCE="false"/>
      </FIELDS>
      <KEYS>
        <KEY NAME="primary" TYPE="primary" FIELDS="id" COMMENT="Primary key for individualfeedback_template"/>
      </KEYS>
      <INDEXES>
        <INDEX NAME="course" UNIQUE="false" FIELDS="course"/>
      </INDEXES>
    </TABLE>
    <TABLE NAME="individualfeedback_item" COMMENT="individualfeedback_items">
      <FIELDS>
        <FIELD NAME="id" TYPE="int" LENGTH="10" NOTNULL="true" SEQUENCE="true"/>
        <FIELD NAME="individualfeedback" TYPE="int" LENGTH="10" NOTNULL="true" DEFAULT="0" SEQUENCE="false"/>
        <FIELD NAME="template" TYPE="int" LENGTH="10" NOTNULL="true" DEFAULT="0" SEQUENCE="false"/>
        <FIELD NAME="name" TYPE="char" LENGTH="255" NOTNULL="true" SEQUENCE="false"/>
        <FIELD NAME="label" TYPE="char" LENGTH="255" NOTNULL="true" SEQUENCE="false"/>
        <FIELD NAME="presentation" TYPE="text" NOTNULL="true" SEQUENCE="false"/>
        <FIELD NAME="typ" TYPE="char" LENGTH="255" NOTNULL="true" SEQUENCE="false"/>
        <FIELD NAME="hasvalue" TYPE="int" LENGTH="1" NOTNULL="true" DEFAULT="0" SEQUENCE="false"/>
        <FIELD NAME="position" TYPE="int" LENGTH="3" NOTNULL="true" DEFAULT="0" SEQUENCE="false"/>
        <FIELD NAME="required" TYPE="int" LENGTH="1" NOTNULL="true" DEFAULT="0" SEQUENCE="false"/>
        <FIELD NAME="dependitem" TYPE="int" LENGTH="10" NOTNULL="true" DEFAULT="0" SEQUENCE="false"/>
        <FIELD NAME="dependvalue" TYPE="char" LENGTH="255" NOTNULL="true" SEQUENCE="false"/>
        <FIELD NAME="options" TYPE="char" LENGTH="255" NOTNULL="true" SEQUENCE="false"/>
      </FIELDS>
      <KEYS>
        <KEY NAME="primary" TYPE="primary" FIELDS="id" COMMENT="Primary key for individualfeedback_item"/>
        <KEY NAME="individualfeedback" TYPE="foreign" FIELDS="individualfeedback" REFTABLE="individualfeedback" REFFIELDS="id"/>
        <KEY NAME="template" TYPE="foreign" FIELDS="template" REFTABLE="individualfeedback_template" REFFIELDS="id"/>
      </KEYS>
    </TABLE>
    <TABLE NAME="individualfeedback_completed" COMMENT="filled out individualfeedback">
      <FIELDS>
        <FIELD NAME="id" TYPE="int" LENGTH="10" NOTNULL="true" SEQUENCE="true"/>
        <FIELD NAME="individualfeedback" TYPE="int" LENGTH="10" NOTNULL="true" DEFAULT="0" SEQUENCE="false"/>
        <FIELD NAME="userid" TYPE="char" LENGTH="255" NOTNULL="true" DEFAULT="0" SEQUENCE="false"/>
        <FIELD NAME="timemodified" TYPE="int" LENGTH="10" NOTNULL="true" DEFAULT="0" SEQUENCE="false"/>
        <FIELD NAME="random_response" TYPE="int" LENGTH="10" NOTNULL="true" DEFAULT="0" SEQUENCE="false"/>
        <FIELD NAME="anonymous_response" TYPE="int" LENGTH="1" NOTNULL="true" DEFAULT="0" SEQUENCE="false"/>
        <FIELD NAME="courseid" TYPE="int" LENGTH="10" NOTNULL="true" DEFAULT="0" SEQUENCE="false"/>
        <FIELD NAME="selfassessment" TYPE="int" LENGTH="1" NOTNULL="true" DEFAULT="0" SEQUENCE="false"/>
      </FIELDS>
      <KEYS>
        <KEY NAME="primary" TYPE="primary" FIELDS="id" COMMENT="Primary key for individualfeedback_completed"/>
        <KEY NAME="individualfeedback" TYPE="foreign" FIELDS="individualfeedback" REFTABLE="individualfeedback" REFFIELDS="id"/>
      </KEYS>
    </TABLE>
    <TABLE NAME="indfeedback_completedtmp" COMMENT="filled out individualfeedback">
      <FIELDS>
        <FIELD NAME="id" TYPE="int" LENGTH="10" NOTNULL="true" SEQUENCE="true"/>
        <FIELD NAME="individualfeedback" TYPE="int" LENGTH="10" NOTNULL="true" DEFAULT="0" SEQUENCE="false"/>
        <FIELD NAME="userid" TYPE="char" LENGTH="255" NOTNULL="true" DEFAULT="0" SEQUENCE="false"/>
        <FIELD NAME="guestid" TYPE="char" LENGTH="255" NOTNULL="true" SEQUENCE="false"/>
        <FIELD NAME="timemodified" TYPE="int" LENGTH="10" NOTNULL="true" DEFAULT="0" SEQUENCE="false"/>
        <FIELD NAME="random_response" TYPE="int" LENGTH="10" NOTNULL="true" DEFAULT="0" SEQUENCE="false"/>
        <FIELD NAME="anonymous_response" TYPE="int" LENGTH="1" NOTNULL="true" DEFAULT="0" SEQUENCE="false"/>
        <FIELD NAME="courseid" TYPE="int" LENGTH="10" NOTNULL="true" DEFAULT="0" SEQUENCE="false"/>
        <FIELD NAME="selfassessment" TYPE="int" LENGTH="1" NOTNULL="true" DEFAULT="0" SEQUENCE="false"/>
      </FIELDS>
      <KEYS>
        <KEY NAME="primary" TYPE="primary" FIELDS="id" COMMENT="Primary key for indfeedback_completedtmp"/>
        <KEY NAME="individualfeedback" TYPE="foreign" FIELDS="individualfeedback" REFTABLE="individualfeedback" REFFIELDS="id"/>
      </KEYS>
    </TABLE>
    <TABLE NAME="individualfeedback_value" COMMENT="values of the completeds">
      <FIELDS>
        <FIELD NAME="id" TYPE="int" LENGTH="10" NOTNULL="true" SEQUENCE="true"/>
        <FIELD NAME="course_id" TYPE="int" LENGTH="10" NOTNULL="true" DEFAULT="0" SEQUENCE="false"/>
        <FIELD NAME="item" TYPE="int" LENGTH="10" NOTNULL="true" DEFAULT="0" SEQUENCE="false"/>
        <FIELD NAME="completed" TYPE="int" LENGTH="10" NOTNULL="true" DEFAULT="0" SEQUENCE="false"/>
        <FIELD NAME="tmp_completed" TYPE="int" LENGTH="10" NOTNULL="true" DEFAULT="0" SEQUENCE="false"/>
        <FIELD NAME="value" TYPE="text" NOTNULL="true" SEQUENCE="false"/>
      </FIELDS>
      <KEYS>
        <KEY NAME="primary" TYPE="primary" FIELDS="id" COMMENT="Primary key for individualfeedback_value"/>
        <KEY NAME="item" TYPE="foreign" FIELDS="item" REFTABLE="individualfeedback_item" REFFIELDS="id"/>
      </KEYS>
      <INDEXES>
        <INDEX NAME="course_id" UNIQUE="false" FIELDS="course_id"/>
        <INDEX NAME="completed_item" UNIQUE="true" FIELDS="completed, item, course_id"/>
      </INDEXES>
    </TABLE>
    <TABLE NAME="individualfeedback_valuetmp" COMMENT="values of the completedstmp">
      <FIELDS>
        <FIELD NAME="id" TYPE="int" LENGTH="10" NOTNULL="true" SEQUENCE="true"/>
        <FIELD NAME="course_id" TYPE="int" LENGTH="10" NOTNULL="true" DEFAULT="0" SEQUENCE="false"/>
        <FIELD NAME="item" TYPE="int" LENGTH="10" NOTNULL="true" DEFAULT="0" SEQUENCE="false"/>
        <FIELD NAME="completed" TYPE="int" LENGTH="10" NOTNULL="true" DEFAULT="0" SEQUENCE="false"/>
        <FIELD NAME="tmp_completed" TYPE="int" LENGTH="10" NOTNULL="true" DEFAULT="0" SEQUENCE="false"/>
        <FIELD NAME="value" TYPE="text" NOTNULL="true" SEQUENCE="false"/>
      </FIELDS>
      <KEYS>
        <KEY NAME="primary" TYPE="primary" FIELDS="id" COMMENT="Primary key for individualfeedback_valuetmp"/>
        <KEY NAME="item" TYPE="foreign" FIELDS="item" REFTABLE="individualfeedback_item" REFFIELDS="id"/>
      </KEYS>
      <INDEXES>
        <INDEX NAME="course_id" UNIQUE="false" FIELDS="course_id"/>
        <INDEX NAME="completed_item" UNIQUE="true" FIELDS="completed, item, course_id"/>
      </INDEXES>
    </TABLE>
    <TABLE NAME="indfeedback_sitecourse_map" COMMENT="individualfeedback sitecourse map">
      <FIELDS>
        <FIELD NAME="id" TYPE="int" LENGTH="10" NOTNULL="true" SEQUENCE="true"/>
        <FIELD NAME="individualfeedbackid" TYPE="int" LENGTH="10" NOTNULL="true" DEFAULT="0" SEQUENCE="false"/>
        <FIELD NAME="courseid" TYPE="int" LENGTH="10" NOTNULL="true" DEFAULT="0" SEQUENCE="false"/>
      </FIELDS>
      <KEYS>
        <KEY NAME="primary" TYPE="primary" FIELDS="id" COMMENT="Primary key for indfeedback_sitecourse_map"/>
        <KEY NAME="individualfeedbackid" TYPE="foreign" FIELDS="individualfeedbackid" REFTABLE="individualfeedback" REFFIELDS="id"/>
      </KEYS>
      <INDEXES>
        <INDEX NAME="courseid" UNIQUE="false" FIELDS="courseid"/>
      </INDEXES>
    </TABLE>
  </TABLES>
</XMLDB>